delta_env/__init__.py
delta_env/cmd.py
delta_env/common.py
delta_env-1.0.0.dist-info/LICENSE.md
delta_env-1.0.0.dist-info/METADATA
delta_env-1.0.0.dist-info/WHEEL
delta_env-1.0.0.dist-info/entry_points.txt
delta_env-1.0.0.dist-info/top_level.txt
delta_env-1.0.0.dist-info/RECORD
