Metadata-Version: 2.1
Name: delta-env
Version: 1.0.0
Summary: A simple tool to analyze how a shell script modifies environment variables
Author-email: Cetin Alanyalioglu <cetinalanyalioglu@gmail.com>
License: MIT License        
Project-URL: Homepage, https://github.com/cetinalanyalioglu/delta-env
Classifier: Programming Language :: Python :: 3 :: Only
Classifier: License :: OSI Approved :: MIT License
Requires-Python: >=3.0.0
License-File: LICENSE.md
Provides-Extra: dev
Requires-Dist: black ; extra == 'dev'
Requires-Dist: flake8 ; extra == 'dev'
Requires-Dist: pip-tools ; extra == 'dev'
Requires-Dist: bumpver ; extra == 'dev'
